_tgvoip.cp36-win32.pyd
_tgvoip.pdb
tgvoip/__init__.py
tgvoip/tgvoip.py
tgvoip/utils.py
pytgvoip-0.0.6.dist-info/COPYING
pytgvoip-0.0.6.dist-info/COPYING.lesser
pytgvoip-0.0.6.dist-info/METADATA
pytgvoip-0.0.6.dist-info/NOTICE
pytgvoip-0.0.6.dist-info/WHEEL
pytgvoip-0.0.6.dist-info/top_level.txt
pytgvoip-0.0.6.dist-info/RECORD
